citelang/__init__.py
citelang/defaults.py
citelang/logger.py
citelang/settings.yml
citelang/version.py
citelang/client/__init__.py
citelang/client/badge.py
citelang/client/cache.py
citelang/client/config.py
citelang/client/contrib.py
citelang/client/credit.py
citelang/client/deps.py
citelang/client/gen.py
citelang/client/graph.py
citelang/client/listing.py
citelang/client/package.py
citelang/client/render.py
citelang/client/shell.py
citelang/main/__init__.py
citelang/main/base.py
citelang/main/cache.py
citelang/main/client.py
citelang/main/colors.py
citelang/main/contrib.py
citelang/main/endpoints.py
citelang/main/http.py
citelang/main/package.py
citelang/main/parser.py
citelang/main/result.py
citelang/main/schemas.py
citelang/main/settings.py
citelang/main/badge/__init__.py
citelang/main/badge/sunburst.html
citelang/main/badge/treemap.html
citelang/main/graph/__init__.py
citelang/main/graph/base.py
citelang/main/graph/cypher.py
citelang/main/graph/dot.py
citelang/main/graph/gexf.py
citelang/main/graph/graph.py
citelang/main/graph/text.py
citelang/main/graph/tree.py
citelang/main/packages/__init__.py
citelang/main/packages/base.py
citelang/main/packages/cpp_cmakelist.py
citelang/main/packages/cran_description.py
citelang/main/packages/github.py
citelang/main/packages/go_mod.py
citelang/main/packages/npm_packages.py
citelang/main/packages/pip_wrapper.py
citelang/main/packages/pypi_requirements.py
citelang/main/packages/python_base.py
citelang/main/packages/ruby_gem.py
citelang/main/packages/spack.py
citelang/tests/__init__.py
citelang/tests/helpers.sh
citelang/tests/test-registry-module.sh
citelang/tests/test_client.sh
citelang/tests/test_packages.py
citelang/tests/test_settings.py
citelang/tests/test_utils.py
citelang/tests/testdata/CMakeLists.txt
citelang/tests/testdata/DESCRIPTION
citelang/tests/testdata/Gemfile
citelang/tests/testdata/go.mod
citelang/tests/testdata/package.json
citelang/tests/testdata/requirements.txt
citelang/tests/testdata/setup.py
citelang-0.0.35.dist-info/LICENSE
citelang-0.0.35.dist-info/METADATA
citelang-0.0.35.dist-info/WHEEL
citelang-0.0.35.dist-info/entry_points.txt
citelang-0.0.35.dist-info/top_level.txt
citelang-0.0.35.dist-info/RECORD
