Metadata-Version: 2.1
Name: citelang
Version: 0.0.35
Summary: Credit parser and markdown language for scientific software.
Home-page: https://github.com/vsoch/citelang
Author: Vanessa Sochat
Author-email: vsoch@users.noreply.github.com
Maintainer: Vanessa Sochat
License: LICENSE
Keywords: credit,software,rseng,research software
Classifier: Intended Audience :: Science/Research
Classifier: Intended Audience :: Developers
Classifier: License :: OSI Approved :: Mozilla Public License 2.0 (MPL 2.0)
Classifier: Programming Language :: C
Classifier: Programming Language :: Python
Classifier: Topic :: Software Development
Classifier: Topic :: Scientific/Engineering
Classifier: Operating System :: Unix
Classifier: Programming Language :: Python :: 3.8
License-File: LICENSE
Requires-Dist: rich
Requires-Dist: pyaml
Requires-Dist: jsonschema
Requires-Dist: requests
Requires-Dist: colour
Provides-Extra: all
Requires-Dist: rich; extra == "all"
Requires-Dist: pyaml; extra == "all"
Requires-Dist: jsonschema; extra == "all"
Requires-Dist: requests; extra == "all"
Requires-Dist: colour; extra == "all"
Requires-Dist: pytest>=4.6.2; extra == "all"
Requires-Dist: plotly; extra == "all"
Requires-Dist: kaleido; extra == "all"
Provides-Extra: badge
Requires-Dist: plotly; extra == "badge"
Requires-Dist: kaleido; extra == "badge"
